Metadata-Version: 2.1
Name: whisper-cli-tool
Version: 1.0.2
Summary: Do transcriptions of audiofiles using the whisper-1 model from OpenAI.
Home-page: 
Author: João Nogueira
Author-email: joaopcnogueira@gmail.com
License:                                  Apache License
License-File: LICENSE
